custom_step/__init__.py
custom_step/_version.py
custom_step/colourchooser.py
custom_step/custom.py
custom_step/custom_parameters.py
custom_step/custom_step.py
custom_step/findwindow.py
custom_step/fontchooser.py
custom_step/highlighter.py
custom_step/linenumbers.py
custom_step/textarea.py
custom_step/texteditor.py
custom_step/tk_custom.py
custom_step/data/references.bib
custom_step-2023.12.12.dist-info/AUTHORS.rst
custom_step-2023.12.12.dist-info/LICENSE
custom_step-2023.12.12.dist-info/METADATA
custom_step-2023.12.12.dist-info/WHEEL
custom_step-2023.12.12.dist-info/entry_points.txt
custom_step-2023.12.12.dist-info/top_level.txt
custom_step-2023.12.12.dist-info/RECORD
