Metadata-Version: 2.1
Name: custom-step
Version: 2023.12.12
Summary: A SEAMM plug-in for custom Python scripts in a flowchart.
Home-page: https://github.com/molssi-seamm/custom_step
Author: Paul Saxe
Author-email: psaxe@molssi.org
License: BSD-3-Clause
Keywords: SEAMM,plug-in,flowchart,custom,python
Platform: Linux
Platform: Mac OS-X
Platform: Unix
Platform: Windows
Classifier: Development Status :: 5 - Production/Stable
Classifier: Intended Audience :: Science/Research
Classifier: License :: OSI Approved :: BSD License
Classifier: Natural Language :: English
Classifier: Programming Language :: Python :: 3 :: Only
Classifier: Programming Language :: Python :: 3.8
Classifier: Programming Language :: Python :: 3.9
License-File: LICENSE
License-File: AUTHORS.rst
Requires-Dist: PyYAML
Requires-Dist: seamm
Requires-Dist: seamm-util
